Workbook

Sheet Supuestos
A1: Modelo de Capacidad — Taller CÚADRO (v3)
A2: Base de medición: Operaciones_Por_Linea (2). Celdas AMARILLAS editables.
A4: Parámetro | B4: Valor | C4: Unidad | D4: Origen / nota
A5: Días laborables por mes | B5: 20 | C5: días | D5: Convención del taller
A6: Operaciones por pieza — Modelo 1 | B6: 8.9 | C6: ops/pza | D6: Convención del propio archivo de medición: 2.940 ops ÷ 367,5 pzas = 8,00
A7: Stock de seguridad | B7: 0.1 | C7: % | D7: Instrucción de Gerencia
A8: Tasa de reproceso — Actual (sobre OPERACIONES) | B8: 0.0576 | C8: % | D8: MEDIDO: 3.391 ops de reproceso / 58.880 ops. NO usar aquí el 16,14%: ese es el % de PIEZAS rechazadas, no de operaciones.
A9: Tasa de reproceso — Escenario A | B9: 0.048 | C9: % | D9: SUPUESTO. Se renuevan 4 de 18 posiciones
A10: Tasa de reproceso — Escenario B | B10: 0.04 | C10: % | D10: SUPUESTO. Se renuevan 8 posiciones
A11: Tasa de reproceso — Escenario C | B11: 0.04 | C11: % | D11: SUPUESTO. Igual que B (la collaretera de L5 no toca las líneas 1-4)
A12: Tasa de reproceso — Escenario D | B12: 0.035 | C12: % | D12: SUPUESTO. 8 posiciones renovadas más una línea 100% nueva
A13: Ganancia por máquina electrónica | B13: 0.08 | C13: % | D13: SUPUESTO (rango 2%-8%). Corta-hilo + alza-pie sobre SAM de 2,30 min
A14: Capacidad de L3 cedida a la Línea 5 | B14: 0.1 | C14: % | D14: DATO DE PRODUCCIÓN. Se recupera en los escenarios C y D
A15: Demanda mes regular | B15: 4145 | C15: pzas | D15: Dato de Gerencia
A16: Demanda diciembre | B16: 9434 | C16: pzas | D16: Dato de Gerencia
... A23: Ops de COLLARET RUEDO por pieza | B23: 1 | C23: ops | D23: MEDIDO: estudio de tiempos Clásica Algodón
A25: Coherencia de la estructura de operaciones
A26: Suma de ops por tipo (overlock + cuello + ruedo) | B26: =Supuestos!$B$21+Supuestos!$B$22+Supuestos!$B$23 -> 9
A27: ATENCIÓN: si esta suma no coincide con las 'Operaciones por pieza — Modelo 1', los dos modelos describen piezas distintas. Reconciliar antes de presentar.

Sheet Mediciones
A1: Mediciones base por posición de línea
A2: Transcripción literal de Operaciones_Por_Linea (2), hoja 'Operaciones - Taller Diario'. Única fuente de capacidad de este modelo.
A4: Línea | B4: Posición | C4: Máquina | D4: Operación | E4: Cap. teórica | F4: Estatus | G4: Cap. real
A5: Línea 1 | B5: 1 | C5: Overlock | D5: Unión / Montaje | E5: 190 | F5: Disponible | G5: 190
A6: Línea 1 | B6: 2 | C6: Collaret | D6: Recubrir Cuello | E6: 196 | F6: Disponible | G6: 196
A7: Línea 1 | B7: 3 | C7: Overlock | D7: Montaje / Cierre | E7: 198 | F7: Disponible | G7: 198
A8: Línea 1 | B8: 4 | C8: Collaret | D8: Ruedo | E8: 101 | F8: Disponible | G8: 101
A9: Línea 2 | B9: 1 | C9: Overlock | D9: Unión / Montaje | E9: 190 | F9: 80 % | G9: 150
A10: Línea 2 | B10: 2 | C10: Collaret | D10: Recubrir Cuello | E10: 196 | F10: Disponible | G10: 196
A11: Línea 2 | B11: 3 | C11: Overlock | D11: Montaje / Cierre | E11: 198 | F11: Disponible | G11: 198
A12: Línea 2 | B12: 4 | C12: Collaret | D12: Ruedo | E12: 101 | F12: Disponible | G12: 101
A13: Línea 3 | B13: 1 | C13: Overlock | D13: Unión / Montaje | E13: 190 | F13: Disponible | G13: 190
A14: Línea 3 | B14: 2 | C14: Collaret | D14: Recubrir Cuello | E14: 196 | F14: Disponible | G14: 196
A15: Línea 3 | B15: 3 | C15: Overlock | D15: Montaje / Cierre | E15: 198 | F15: Disponible | G15: 198
A16: Línea 3 | B16: 4 | C16: Collaret | D16: Ruedo | E16: 101 | F16: 50 % | G16: 50.5
... A22: Línea 4 | B22: 5 | C22: Collaret | D22: Ruedo | E22: 100 | F22: Inactiva | G22: 0
A23: TOTAL | E23: =SUM(E5:E22) -> 2940 | G23: =SUM(G5:G22) -> 2649.5
A24: Pérdida por fallas (ops/día) | G24: =E23-G23 -> 290.5

Sheet Lineas por Escenario
A1: Cómo queda cada línea en cada escenario
A2: Posición por posición. Verde = máquina nueva. Naranja = máquina averiada que sigue en servicio. Las nuevas rinden nominal × (1 + ganancia electrónica).
A4: Línea | B4: Pos. | C4: Máquina | D4: Operación | E4: Nominal | F4: Actual — estado | G4: Actual — ops/día | H4: A — estado | I4: A — ops/día | J4: B — estado | K4: B — ops/día | L4: C — estado | M4: C — ops/día | N4: D — estado | O4: D — ops/día
A5: Línea 1 | B5: 1 | C5: Overlock | D5: Unión / Montaje | E5: 190 | F5: Disponible | G5: 190 | H5: Disponible | I5: 190 | J5: NUEVA | K5: =$E5*(1+Supuestos!$B$13) -> 205.2 | L5: NUEVA | M5: =$E5*(1+Supuestos!$B$13) -> 205.2 | N5: NUEVA | O5: =$E5*(1+Supuestos!$B$13) -> 205.2
A6: Línea 1 | B6: 2 | C6: Collaret | D6: Recubrir Cuello | E6: 196 | F6: Disponible | G6: 196 | H6: Disponible | I6: 196 | J6: Disponible | K6: 196 | L6: Disponible | M6: 196 | N6: Disponible | O6: 196
A7: Línea 1 | B7: 3 | C7: Overlock | D7: Montaje / Cierre | E7: 198 | F7: Disponible | G7: 198 | H7: Disponible | I7: 198 | J7: Disponible | K7: 198 | L7: Disponible | M7: 198 | N7: Disponible | O7: 198
A8: Línea 1 | B8: 4 | C8: Collaret | D8: Ruedo | E8: 101 | F8: Disponible | G8: 101 | H8: Disponible | I8: 101 | J8: Disponible | K8: 101 | L8: Disponible | M8: 101 | N8: Disponible | O8: 101
A9: Línea 2 | B9: 1 | C9: Overlock | D9: Unión / Montaje | E9: 190 | F9: 80 % | G9: 150 | H9: NUEVA | I9: =$E9*(1+Supuestos!$B$13) -> 205.2 | J9: NUEVA | K9: =$E9*(1+Supuestos!$B$13) -> 205.2 | L9: NUEVA | M9: =$E9*(1+Supuestos!$B$13) -> 205.2 | N9: NUEVA | O9: =$E9*(1+Supuestos!$B$13) -> 205.2
A10: Línea 2 | B10: 2 | C10: Collaret | D10: Recubrir Cuello | E10: 196 | F10: Disponible | G10: 196 | H10: Disponible | I10: 196 | J10: Disponible | K10: 196 | L10: Disponible | M10: 196 | N10: Disponible | O10: 196
A11: Línea 2 | B11: 3 | C11: Overlock | D11: Montaje / Cierre | E11: 198 | F11: Disponible | G11: 198 | H11: Disponible | I11: 198 | J11: Disponible | K11: 198 | L11: Disponible | M11: 198 | N11: Disponible | O11: 198
A12: Línea 2 | B12: 4 | C12: Collaret | D12: Ruedo | E12: 101 | F12: Disponible | G12: 101 | H12: Disponible | I12: 101 | J12: Disponible | K12: 101 | L12: Disponible | M12: 101 | N12: Disponible | O12: 101
A13: Línea 3 | B13: 1 | C13: Overlock | D13: Unión / Montaje | E13: 190 | F13: Disponible | G13: 190 | H13: Disponible | I13: 190 | J13: Disponible | K13: 190 | L13: Disponible | M13: 190 | N13: Disponible | O13: 190
A14: Línea 3 | B14: 2 | C14: Collaret | D14: Recubrir Cuello | E14: 196 | F14: Disponible | G14: 196 | H14: Disponible | I14: 196 | J14: Disponible | K14: 196 | L14: Disponible | M14: 196 | N14: Disponible | O14: 196
A15: Línea 3 | B15: 3 | C15: Overlock | D15: Montaje / Cierre | E15: 198 | F15: Disponible | G15: 198 | H15: Disponible | I15: 198 | J15: Disponible | K15: 198 | L15: Disponible | M15: 198 | N15: Disponible | O15: 198
A16: Línea 3 | B16: 4 | C16: Collaret | D16: Ruedo | E16: 101 | F16: 50 % | G16: 50.5 | H16: NUEVA | I16: =$E16*(1+Supuestos!$B$13) -> 109.08 | J16: NUEVA | K16: =$E16*(1+Supuestos!$B$13) -> 109.08 | L16: NUEVA | M16: =$E16*(1+Supuestos!$B$13) -> 109.08 | N16: NUEVA | O16: =$E16*(1+Supuestos!$B$13) -> 109.08
A17: Línea 3 | B17: 5 | C17: Collaret | D17: Ruedo | E17: 100 | F17: Inactiva | G17: 0 | H17: NUEVA | I17: =$E17*(1+Supuestos!$B$13) -> 108 | J17: NUEVA | K17: =$E17*(1+Supuestos!$B$13) -> 108 | L17: NUEVA | M17: =$E17*(1+Supuestos!$B$13) -> 108 | N17: NUEVA | O17: =$E17*(1+Supuestos!$B$13) -> 108
A18: Línea 4 | B18: 1 | C18: Overlock | D18: Unión / Montaje | E18: 190 | F18: Disponible | G18: 190 | H18: Disponible | I18: 190 | J18: Disponible | K18: 190 | L18: Disponible | M18: 190 | N18: Disponible | O18: 190
A19: Línea 4 | B19: 2 | C19: Collaret | D19: Recubrir Cuello | E19: 196 | F19: Disponible | G19: 196 | H19: Disponible | I19: 196 | J19: Disponible | K19: 196 | L19: Disponible | M19: 196 | N19: Disponible | O19: 196
A20: Línea 4 | B20: 3 | C20: Overlock | D20: Montaje / Cierre | E20: 198 | F20: Disponible | G20: 198 | H20: Disponible | I20: 198 | J20: Disponible | K20: 198 | L20: Disponible | M20: 198 | N20: Disponible | O20: 198
A21: Línea 4 | B21: 4 | C21: Collaret | D21: Ruedo | E21: 101 | F21: Disponible | G21: 101 | H21: Disponible | I21: 101 | J21: NUEVA | K21: =$E21*(1+Supuestos!$B$13) -> 109.08 | L21: NUEVA | M21: =$E21*(1+Supuestos!$B$13) -> 109.08 | N21: NUEVA | O21: =$E21*(1+Supuestos!$B$13) -> 109.08
A22: Línea 4 | B22: 5 | C22: Collaret | D22: Ruedo | E22: 100 | F22: Inactiva | G22: 0 | H22: NUEVA | I22: =$E22*(1+Supuestos!$B$13) -> 108 | J22: NUEVA | K22: =$E22*(1+Supuestos!$B$13) -> 108 | L22: NUEVA | M22: =$E22*(1+Supuestos!$B$13) -> 108 | N22: NUEVA | O22: =$E22*(1+Supuestos!$B$13) -> 108
A23: Línea 1 | B23: 5 | C23: Collaret | D23: Ruedo | E23: 100 | F23: No existe | G23: 0 | H23: No existe | I23: 0 | J23: NUEVA | K23: =$E23*(1+Supuestos!$B$13) -> 108 | L23: NUEVA | M23: =$E23*(1+Supuestos!$B$13) -> 108 | N23: NUEVA | O23: =$E23*(1+Supuestos!$B$13) -> 108
A24: Línea 2 | B24: 5 | C24: Collaret | D24: Ruedo | E24: 100 | F24: No existe | G24: 0 | H24: No existe | I24: 0 | J24: NUEVA | K24: =$E24*(1+Supuestos!$B$13) -> 108 | L24: NUEVA | M24: =$E24*(1+Supuestos!$B$13) -> 108 | N24: NUEVA | O24: =$E24*(1+Supuestos!$B$13) -> 108
A25: Línea 6 | B25: 1 | C25: Overlock | D25: Unión / Montaje | E25: 190 | F25: No existe | G25: 0 | H25: No existe | I25: 0 | J25: No existe | K25: 0 | L25: No existe | M25: 0 | N25: NUEVA | O25: =$E25*(1+Supuestos!$B$13) -> 205.2
A26: Línea 6 | B26: 2 | C26: Collaret | D26: Recubrir Cuello | E26: 196 | F26: No existe | G26: 0 | H26: No existe | I26: 0 | J26: No existe | K26: 0 | L26: No existe | M26: 0 | N26: NUEVA | O26: =$E26*(1+Supuestos!$B$13) -> 211.68
A27: Línea 6 | B27: 3 | C27: Overlock | D27: Montaje / Cierre | E27: 198 | F27: No existe | G27: 0 | H27: No existe | I27: 0 | J27: No existe | K27: 0 | L27: No existe | M27: 0 | N27: NUEVA | O27: =$E27*(1+Supuestos!$B$13) -> 213.84
A28: Línea 6 | B28: 4 | C28: Collaret | D28: Ruedo | E28: 101 | F28: No existe | G28: 0 | H28: No existe | I28: 0 | J28: No existe | K28: 0 | L28: No existe | M28: 0 | N28: NUEVA | O28: =$E28*(1+Supuestos!$B$13) -> 109.08
A29: Línea 6 | B29: 5 | C29: Collaret | D29: Ruedo | E29: 100 | F29: No existe | G29: 0 | H29: No existe | I29: 0 | J29: No existe | K29: 0 | L29: No existe | M29: 0 | N29: NUEVA | O29: =$E29*(1+Supuestos!$B$13) -> 108
A31: TOTAL OPS/DÍA POR LÍNEA (ya descontada la cesión de L3 a la Línea 5)
A32: Línea | F32: Actual ops/día | H32: A ops/día | J32: B ops/día | L32: C ops/día | N32: D ops/día
A33: Línea 1 | F33: =(G5+G6+G7+G8+G23) -> 685 | H33: =(I5+I6+I7+I8+I23) -> 685 | J33: =(K5+K6+K7+K8+K23) -> 808.2 | L33: =(M5+M6+M7+M8+M23) -> 808.2 | N33: =(O5+O6+O7+O8+O23) -> 808.2
A34: Línea 2 | F34: =(G9+G10+G11+G12+G24) -> 645 | H34: =(I9+I10+I11+I12+I24) -> 700.2 | J34: =(K9+K10+K11+K12+K24) -> 808.2 | L34: =(M9+M10+M11+M12+M24) -> 808.2 | N34: =(O9+O10+O11+O12+O24) -> 808.2
A35: Línea 3 | F35: =(G13+G14+G15+G16+G17)*(1-Supuestos!$B$14) -> 571.05 | H35: =(I13+I14+I15+I16+I17)*(1-Supuestos!$B$14) -> 720.972 | J35: =(K13+K14+K15+K16+K17)*(1-Supuestos!$B$14) -> 720.972 | L35: =(M13+M14+M15+M16+M17) -> 801.08 | N35: =(O13+O14+O15+O16+O17) -> 801.08
A36: Línea 4 | F36: =(G18+G19+G20+G21+G22) -> 685 | H36: =(I18+I19+I20+I21+I22) -> 793 | J36: =(K18+K19+K20+K21+K22) -> 801.08 | L36: =(M18+M19+M20+M21+M22) -> 801.08 | N36: =(O18+O19+O20+O21+O22) -> 801.08
A37: Línea 6 | F37: =(G25+G26+G27+G28+G29) -> 0 | H37: =(I25+I26+I27+I28+I29) -> 0 | J37: =(K25+K26+K27+K28+K29) -> 0 | L37: =(M25+M26+M27+M28+M29) -> 0 | N37: =(O25+O26+O27+O28+O29) -> 847.8
A38: TOTAL TALLER | F38: =SUM(F33:F37) -> 2586.05 | H38: =SUM(H33:H37) -> 2899.172 | J38: =SUM(J33:J37) -> 3138.452 | L38: =SUM(L33:L37) -> 3218.56 | N38: =SUM(N33:N37) -> 4066.36
A40: La Línea 3 aparece con su capacidad neta: en Actual, A y B se le descuenta el 10% que presta a la Línea 5. En C y D ese descuento desaparece porque la Línea 5 recibe collaretera propia.
A41: La collaretera de la Línea 5 del escenario C no figura en esta tabla porque la Línea 5 no forma parte del techo de las líneas 1-4; su efecto se ve en la recuperación de la Línea 3.

Sheet Escenarios
A1: En qué consiste cada escenario
A2: Descripción operativa de las cuatro alternativas de inversión
A4: Escenario | B4: Qué se compra | C4: En qué consiste / qué problema resuelve | D4: Nº máq. | E4: Inversión US$
A5: A — Reposición estricta | B5: 3 collareteras de ruedo (2 para L3, 1 para L4) + 1 overlock (L2) | C5: Comprar exactamente lo que hoy está averiado, ni una máquina más. Reemplaza el overlock de Unión/Montaje de L2 (hoy al 80%), la collaretera de ruedo de L3 (al 50%), la collaretera de ruedo inactiva de L3 y la collaretera de ruedo inactiva de L4. Restituye las 290,5 ops/día perdidas y devuelve el taller a su techo teórico de 2.940 ops/día. No agrega ninguna posición nueva: la estructura de las líneas queda igual a la de hoy. | D5: 4 | E5: =Inversion!$H$5 -> 10400
A6: B — Propuesta de Producción | B6: 6 collareteras de ruedo + 2 overlock de reemplazo | C6: Además de reponer lo averiado, iguala las cuatro líneas. Hoy L3 y L4 tienen dos posiciones de ruedo y L1 y L2 solo una. Se reemplazan las cuatro collareteras de L3 y L4, se agrega una quinta posición de ruedo a L1 y otra a L2, y se reemplaza un overlock en L1 y otro en L2. Las cuatro líneas quedan con la misma estructura de 5 máquinas: 2 overlock + 1 collaret de cuello + 2 collaret de ruedo. | D6: 8 | E6: =Inversion!$H$6 -> 20800
A7: C — B + Línea 5 autónoma | B7: Todo lo de B + 1 collaretera para la Línea 5 | C7: Corrige un préstamo de capacidad que hoy no aparece en ningún reporte: algunos modelos de la Línea 5 necesitan la Línea 3 para manufacturar su parte interna y consumen el 10% de su capacidad mensual. Al dotar a la Línea 5 de collaretera propia, la Línea 3 recupera ese 10% para producción propia y deja de relentizarse en simultáneo con L5. | D7: 9 | E7: =Inversion!$H$7 -> 23800
A8: D — C + línea nueva | B8: Todo lo de C + una Línea 6 completa: 2 overlock + 1 collaret de cuello + 2 collaret de ruedo | C8: Suma una quinta línea de confección con la misma estructura de 5 máquinas del escenario B. Es el único escenario que amplía la planta en lugar de repararla o reequilibrarla, y por tanto el único que mueve el techo de forma sustancial. Requiere dotación de personal para la línea nueva, costo no incluido en la cifra de inversión. | D8: 14 | E8: =Inversion!$H$8 -> 34500
A10: Los escenarios son acumulativos: A ⊂ B ⊂ C ⊂ D. Comprar A no invalida pasar después a B, C o D.

Sheet Capacidad
A1: Capacidad instalada por escenario
A2: Modelo 1 = conversión por operaciones. Modelo 2 = balance de estaciones (criterio de planificación).
A4: Capacidad neta por tipo (ops/día) | B4: Actual | C4: A | D4: B | E4: C | F4: D | G4: Ops/pza
A5: Overlock | B5: ='Lineas por Escenario'!G5+'Lineas por Escenario'!G7+'Lineas por Escenario'!G9+'Lineas por Escenario'!G11+'Lineas por Escenario'!G13*(1-Supuestos!$B$14)+'Lineas por Escenario'!G15*(1-Supuestos!$B$14)+'Lineas por Escenario'!G18+'Lineas por Escenario'!G20+'Lineas por Escenario'!G25+'Lineas por Escenario'!G27 -> 1473.2 | C5: ='Lineas por Escenario'!I5+'Lineas por Escenario'!I7+'Lineas por Escenario'!I9+'Lineas por Escenario'!I11+'Lineas por Escenario'!I13*(1-Supuestos!$B$14)+'Lineas por Escenario'!I15*(1-Supuestos!$B$14)+'Lineas por Escenario'!I18+'Lineas por Escenario'!I20+'Lineas por Escenario'!I25+'Lineas por Escenario'!I27 -> 1528.4 | D5: ='Lineas por Escenario'!K5+'Lineas por Escenario'!K7+'Lineas por Escenario'!K9+'Lineas por Escenario'!K11+'Lineas por Escenario'!K13*(1-Supuestos!$B$14)+'Lineas por Escenario'!K15*(1-Supuestos!$B$14)+'Lineas por Escenario'!K18+'Lineas por Escenario'!K20+'Lineas por Escenario'!K25+'Lineas por Escenario'!K27 -> 1543.6 | E5: ='Lineas por Escenario'!M5+'Lineas por Escenario'!M7+'Lineas por Escenario'!M9+'Lineas por Escenario'!M11+'Lineas por Escenario'!M13+'Lineas por Escenario'!M15+'Lineas por Escenario'!M18+'Lineas por Escenario'!M20+'Lineas por Escenario'!M25+'Lineas por Escenario'!M27 -> 1582.4 | F5: ='Lineas por Escenario'!O5+'Lineas por Escenario'!O7+'Lineas por Escenario'!O9+'Lineas por Escenario'!O11+'Lineas por Escenario'!O13+'Lineas por Escenario'!O15+'Lineas por Escenario'!O18+'Lineas por Escenario'!O20+'Lineas por Escenario'!O25+'Lineas por Escenario'!O27 -> 2001.44 | G5: =Supuestos!$B$21 -> 7
A6: Collaret Cuello | B6: ='Lineas por Escenario'!G6+'Lineas por Escenario'!G10+'Lineas por Escenario'!G14*(1-Supuestos!$B$14)+'Lineas por Escenario'!G19+'Lineas por Escenario'!G26 -> 764.4 | C6: ='Lineas por Escenario'!I6+'Lineas por Escenario'!I10+'Lineas por Escenario'!I14*(1-Supuestos!$B$14)+'Lineas por Escenario'!I19+'Lineas por Escenario'!I26 -> 764.4 | D6: ='Lineas por Escenario'!K6+'Lineas por Escenario'!K10+'Lineas por Escenario'!K14*(1-Supuestos!$B$14)+'Lineas por Escenario'!K19+'Lineas por Escenario'!K26 -> 764.4 | E6: ='Lineas por Escenario'!M6+'Lineas por Escenario'!M10+'Lineas por Escenario'!M14+'Lineas por Escenario'!M19+'Lineas por Escenario'!M26 -> 784 | F6: ='Lineas por Escenario'!O6+'Lineas por Escenario'!O10+'Lineas por Escenario'!O14+'Lineas por Escenario'!O19+'Lineas por Escenario'!O26 -> 995.68 | G6: =Supuestos!$B$22 -> 1
A7: Collaret Ruedo | B7: ='Lineas por Escenario'!G8+'Lineas por Escenario'!G12+'Lineas por Escenario'!G16*(1-Supuestos!$B$14)+'Lineas por Escenario'!G17*(1-Supuestos!$B$14)+'Lineas por Escenario'!G21+'Lineas por Escenario'!G22+'Lineas por Escenario'!G23+'Lineas por Escenario'!G24+'Lineas por Escenario'!G28+'Lineas por Escenario'!G29 -> 348.45 | C7: ='Lineas por Escenario'!I8+'Lineas por Escenario'!I12+'Lineas por Escenario'!I16*(1-Supuestos!$B$14)+'Lineas por Escenario'!I17*(1-Supuestos!$B$14)+'Lineas por Escenario'!I21+'Lineas por Escenario'!I22+'Lineas por Escenario'!I23+'Lineas por Escenario'!I24+'Lineas por Escenario'!I28+'Lineas por Escenario'!I29 -> 606.372 | D7: ='Lineas por Escenario'!K8+'Lineas por Escenario'!K12+'Lineas por Escenario'!K16*(1-Supuestos!$B$14)+'Lineas por Escenario'!K17*(1-Supuestos!$B$14)+'Lineas por Escenario'!K21+'Lineas por Escenario'!K22+'Lineas por Escenario'!K23+'Lineas por Escenario'!K24+'Lineas por Escenario'!K28+'Lineas por Escenario'!K29 -> 830.452 | E7: ='Lineas por Escenario'!M8+'Lineas por Escenario'!M12+'Lineas por Escenario'!M16+'Lineas por Escenario'!M17+'Lineas por Escenario'!M21+'Lineas por Escenario'!M22+'Lineas por Escenario'!M23+'Lineas por Escenario'!M24+'Lineas por Escenario'!M28+'Lineas por Escenario'!M29 -> 852.16 | F7: ='Lineas por Escenario'!O8+'Lineas por Escenario'!O12+'Lineas por Escenario'!O16+'Lineas por Escenario'!O17+'Lineas por Escenario'!O21+'Lineas por Escenario'!O22+'Lineas por Escenario'!O23+'Lineas por Escenario'!O24+'Lineas por Escenario'!O28+'Lineas por Escenario'!O29 -> 1069.24 | G7: =Supuestos!$B$23 -> 1
A8: TOTAL ops/día | B8: =SUM(B5:B7) -> 2586.05 | C8: =SUM(C5:C7) -> 2899.172 | D8: =SUM(D5:D7) -> 3138.452 | E8: =SUM(E5:E7) -> 3218.56 | F8: =SUM(F5:F7) -> 4066.36
A10: MODELO 1 — Conversión por operaciones
A11: Concepto | B11: Actual | C11: A | D11: B | E11: C | F11: D
A12: Ops/mes | B12: =B8*Supuestos!$B$5 -> 51721 | C12: =C8*Supuestos!$B$5 -> 57983.44 | D12: =D8*Supuestos!$B$5 -> 62769.04 | E12: =E8*Supuestos!$B$5 -> 64371.2 | F12: =F8*Supuestos!$B$5 -> 81327.2
A13: Ops/mes netas de reproceso | B13: =B12*(1-Supuestos!$B$8) -> 48741.87 | C13: =C12*(1-Supuestos!$B$9) -> 55200.235 | D13: =D12*(1-Supuestos!$B$10) -> 60258.278 | E13: =E12*(1-Supuestos!$B$11) -> 61796.352 | F13: =F12*(1-Supuestos!$B$12) -> 78480.748
A14: PIEZAS/MES bruto | B14: =B12/Supuestos!$B$6 -> 5811.3483 | C14: =C12/Supuestos!$B$6 -> 6514.9933 | D14: =D12/Supuestos!$B$6 -> 7052.7011 | E14: =E12/Supuestos!$B$6 -> 7232.7191 | F14: =F12/Supuestos!$B$6 -> 9137.8876
A15: PIEZAS/MES netas de reproceso | B15: =B13/Supuestos!$B$6 -> 5476.6147 | C15: =C13/Supuestos!$B$6 -> 6202.2736 | D15: =D13/Supuestos!$B$6 -> 6770.5931 | E15: =E13/Supuestos!$B$6 -> 6943.4103 | F15: =F13/Supuestos!$B$6 -> 8818.0616
A17: MODELO 2 — Balance de estaciones (criterio de planificación)
A18: Restricción activa = la estación que menos piezas habilita. Comprar fuera de la restricción no aumenta la producción.
A19: Concepto | B19: Actual | C19: A | D19: B | E19: C | F19: D
A20: Piezas/día que habilita Overlock | B20: =B5/$G$5 -> 210.45714 | C20: =C5/$G$5 -> 218.34286 | D20: =D5/$G$5 -> 220.51429 | E20: =E5/$G$5 -> 226.05714 | F20: =F5/$G$5 -> 285.92
A21: Piezas/día que habilita Collaret Cuello | B21: =B6/$G$6 -> 764.4 | C21: =C6/$G$6 -> 764.4 | D21: =D6/$G$6 -> 764.4 | E21: =E6/$G$6 -> 784 | F21: =F6/$G$6 -> 995.68
A22: Piezas/día que habilita Collaret Ruedo | B22: =B7/$G$7 -> 348.45 | C22: =C7/$G$7 -> 606.372 | D22: =D7/$G$7 -> 830.452 | E22: =E7/$G$7 -> 852.16 | F22: =F7/$G$7 -> 1069.24
A23: PIEZAS/DÍA (restricción activa) | B23: =MIN(B20:B22) -> 210.45714 | C23: =MIN(C20:C22) -> 218.34286 | D23: =MIN(D20:D22) -> 220.51429 | E23: =MIN(E20:E22) -> 226.05714 | F23: =MIN(F20:F22) -> 285.92
A24: Restricción activa | B24: =INDEX({"Overlock";"Collaret Cuello";"Collaret Ruedo"},MATCH(B23,B20:B22,0)) -> Overlock | C24: =INDEX({"Overlock";"Collaret Cuello";"Collaret Ruedo"},MATCH(C23,C20:C22,0)) -> Overlock | D24: =INDEX({"Overlock";"Collaret Cuello";"Collaret Ruedo"},MATCH(D23,D20:D22,0)) -> Overlock | E24: =INDEX({"Overlock";"Collaret Cuello";"Collaret Ruedo"},MATCH(E23,E20:E22,0)) -> Overlock | F24: =INDEX({"Overlock";"Collaret Cuello";"Collaret Ruedo"},MATCH(F23,F20:F22,0)) -> Overlock
A25: PIEZAS/MES bruto | B25: =B23*Supuestos!$B$5 -> 4209.1429 | C25: =C23*Supuestos!$B$5 -> 4366.8571 | D25: =D23*Supuestos!$B$5 -> 4410.2857 | E25: =E23*Supuestos!$B$5 -> 4521.1429 | F25: =F23*Supuestos!$B$5 -> 5718.4
A26: PIEZAS/MES netas de reproceso | B26: =B23*Supuestos!$B$5*(1-Supuestos!$B$8) -> 3966.6962 | C26: =C23*Supuestos!$B$5*(1-Supuestos!$B$9) -> 4157.248 | D26: =D23*Supuestos!$B$5*(1-Supuestos!$B$10) -> 4233.8743 | E26: =E23*Supuestos!$B$5*(1-Supuestos!$B$11) -> 4340.2971 | F26: =F23*Supuestos!$B$5*(1-Supuestos!$B$12) -> 5518.256

Sheet Demanda y Deficit
A1: Demanda y déficit por escenario
A2: Capacidad comparada = Modelo 2 (balance de estaciones), piezas/mes netas de reproceso
A4: Escenario de demanda | B4: Piezas/mes (con SS) | C4: Actual | D4: A | E4: B | F4: C | G4: D
A5: 1. Mes regular | B5: =Supuestos!$B$15*(1+Supuestos!$B$7) -> 4559.5 | C5: =Capacidad!B$26-$B5 -> -592.80377 | D5: =Capacidad!C$26-$B5 -> -402.252 | E5: =Capacidad!D$26-$B5 -> -325.62571 | F5: =Capacidad!E$26-$B5 -> -219.20286 | G5: =Capacidad!F$26-$B5 -> 958.756
A6: 2. Diciembre como mes aislado | B6: =Supuestos!$B$16*(1+Supuestos!$B$7) -> 10377.4 | C6: =Capacidad!B$26-$B6 -> -6410.7038 | D6: =Capacidad!C$26-$B6 -> -6220.152 | E6: =Capacidad!D$26-$B6 -> -6143.5257 | F6: =Capacidad!E$26-$B6 -> -6037.1029 | G6: =Capacidad!F$26-$B6 -> -4859.144
A7: 3. Zafra Oct-Dic (promedio mensual) | B7: =(Supuestos!$B$15*2+Supuestos!$B$16)*(1+Supuestos!$B$7)/3 -> 6498.8 | C7: =Capacidad!B$26-$B7 -> -2532.1038 | D7: =Capacidad!C$26-$B7 -> -2341.552 | E7: =Capacidad!D$26-$B7 -> -2264.9257 | F7: =Capacidad!E$26-$B7 -> -2158.5029 | G7: =Capacidad!F$26-$B7 -> -980.544
A8: 4. Zafra + 1 tienda nueva (fin 2026) | B8: =((Supuestos!$B$15*2+Supuestos!$B$16)*(1+Supuestos!$B$19/Supuestos!$B$18)+Supuestos!$B$17*Supuestos!$B$19)*(1+Supuestos!$B$7)/3 -> 9511.15 | C8: =Capacidad!B$26-$B8 -> -5544.4538 | D8: =Capacidad!C$26-$B8 -> -5353.902 | E8: =Capacidad!D$26-$B8 -> -5277.2757 | F8: =Capacidad!E$26-$B8 -> -5170.8529 | G8: =Capacidad!F$26-$B8 -> -3992.894
A9: 5. Mes regular 2027 (red completa) | B9: =Supuestos!$B$15*((Supuestos!$B$18+Supuestos!$B$19+Supuestos!$B$20)/Supuestos!$B$18)*(1+Supuestos!$B$7) -> 6839.25 | C9: =Capacidad!B$26-$B9 -> -2872.5538 | D9: =Capacidad!C$26-$B9 -> -2682.002 | E9: =Capacidad!D$26-$B9 -> -2605.3757 | F9: =Capacidad!E$26-$B9 -> -2498.9529 | G9: =Capacidad!F$26-$B9 -> -1320.994
A10: 6. Zafra 2027 + 3 tiendas | B10: =((Supuestos!$B$15*2+Supuestos!$B$16)*((Supuestos!$B$18+Supuestos!$B$19+Supuestos!$B$20)/Supuestos!$B$18)+Supuestos!$B$17*Supuestos!$B$20)*(1+Supuestos!$B$7)/3 -> 16348.2 | C10: =Capacidad!B$26-$B10 -> -12381.504 | D10: =Capacidad!C$26-$B10 -> -12190.952 | E10: =Capacidad!D$26-$B10 -> -12114.326 | F10: =Capacidad!E$26-$B10 -> -12007.903 | G10: =Capacidad!F$26-$B10 -> -10829.944
A12: Capacidad de referencia (piezas/mes) | C12: =Capacidad!B26 -> 3966.6962 | D12: =Capacidad!C26 -> 4157.248 | E12: =Capacidad!D26 -> 4233.8743 | F12: =Capacidad!E26 -> 4340.2971 | G12: =Capacidad!F26 -> 5518.256
A14: Positivo = superávit · Negativo (rojo) = déficit de piezas por mes

Sheet Inversion
A1: Lista de compra por escenario
A2: Precios: presupuesto La Máquina 2005 (JACK), 23-abr-2026 — revalidar antes de la orden
A3: Precio unit. US$ | B3: 3000 | C3: 1900 | D3: 1400
A4: Escenario | B4: K7-35AC ruedo | C4: W5E/ULT cuello | D4: C7-4 overlock | E4: US$ ruedo | F4: US$ cuello | G4: US$ overlock | H4: TOTAL US$
A5: A | B5: 3 | C5: 0 | D5: 1 | E5: =B5*B$3 -> 9000 | F5: =C5*C$3 -> 0 | G5: =D5*D$3 -> 1400 | H5: =SUM(E5:G5) -> 10400
A6: B | B6: 6 | C6: 0 | D6: 2 | E6: =B6*B$3 -> 18000 | F6: =C6*C$3 -> 0 | G6: =D6*D$3 -> 2800 | H6: =SUM(E6:G6) -> 20800
A7: C | B7: 7 | C7: 0 | D7: 2 | E7: =B7*B$3 -> 21000 | F7: =C7*C$3 -> 0 | G7: =D7*D$3 -> 2800 | H7: =SUM(E7:G7) -> 23800
A8: D | B8: 9 | C8: 1 | D8: 4 | E8: =B8*B$3 -> 27000 | F8: =C8*C$3 -> 1900 | G8: =D8*D$3 -> 5600 | H8: =SUM(E8:G8) -> 34500
A10: Costo incremental frente al escenario anterior
A11: A vs hoy | B11: =H5 -> 10400
A12: B vs A | B12: =H6-H5 -> 10400
A13: C vs B | B13: =H7-H6 -> 3000
A14: D vs C | B14: =H8-H7 -> 10700
A16: El escenario D no incluye el costo de la dotación de personal de la línea nueva.
